ditat_etl/__init__.py
ditat_etl/databases/__init__.py
ditat_etl/databases/postgres.py
ditat_etl/hubspot/__init__.py
ditat_etl/hubspot/main.py
ditat_etl/outreach/__init__.py
ditat_etl/outreach/main.py
ditat_etl/outreach/scopes.py
ditat_etl/salesforce/__init__.py
ditat_etl/salesforce/data_ingestion.py
ditat_etl/salesforce/main.py
ditat_etl/time/__init__.py
ditat_etl/time/timer.py
ditat_etl/url/__init__.py
ditat_etl/url/domains_ignored.txt
ditat_etl/url/functions.py
ditat_etl/url/proxies.json
ditat_etl/url/scraper.py
ditat_etl/url/url.py
ditat_etl/url/wrappers.py
ditat_etl/utils/__init__.py
ditat_etl/utils/country_codes.csv
ditat_etl/utils/functions.py
ditat_etl/utils/phones.py
ditat_etl/utils/enrichment/__init__.py
ditat_etl/utils/enrichment/peopledatalabs/__init__.py
ditat_etl/utils/enrichment/peopledatalabs/ae_result_columns.json
ditat_etl/utils/enrichment/peopledatalabs/as_result_columns.json
ditat_etl/utils/enrichment/peopledatalabs/main.py
ditat_etl/utils/enrichment/peopledatalabs/pe_result_columns.json
ditat_etl/utils/enrichment/peopledatalabs/ps_result_columns.json
ditat_etl/utils/entity_resolution/__init__.py
ditat_etl/utils/entity_resolution/country_standard.py
ditat_etl/utils/entity_resolution/domains_ignored.txt
ditat_etl/utils/entity_resolution/industry_naics.py
ditat_etl/utils/entity_resolution/industry_standard.py
ditat_etl/utils/entity_resolution/matcher.py
ditat_etl/utils/entity_resolution/naics.csv
ditat_etl/utils/entity_resolution/state_standard.py
ditat_etl/utils/entity_resolution/us_states.csv
ditat_etl/utils/notification/__init__.py
ditat_etl/utils/notification/slack/__init__.py
ditat_etl/utils/notification/slack/main.py
ditat_etl/utils/search/__init__.py
ditat_etl/utils/search/entity_search.py
ditat_etl-2.6.29.dist-info/LICENSE
ditat_etl-2.6.29.dist-info/METADATA
ditat_etl-2.6.29.dist-info/WHEEL
ditat_etl-2.6.29.dist-info/top_level.txt
ditat_etl-2.6.29.dist-info/RECORD
