Metadata-Version: 2.1
Name: ditat-etl
Version: 2.6.29
Summary: Multiple tools and utilities for ETL pipelines and others.
Home-page: https://github.com/ditat-llc/ditat_etl
Author: ditat.io
Author-email: tomas@ditat.io
Requires-Python: >=3.8
License-File: LICENSE
Requires-Dist: pandas
Requires-Dist: psycopg2-binary
Requires-Dist: requests
Requires-Dist: pysocks
Requires-Dist: selenium
Requires-Dist: phonenumbers
Requires-Dist: boto3
Requires-Dist: simple-salesforce
Requires-Dist: spacy
Requires-Dist: slackclient
Requires-Dist: bs4
